tmt/__init__.py
tmt/tmt_tui.py
tmt/configs/__init__.py
tmt/configs/parser.py
tmt/decorators/__init__.py
tmt/decorators/recorder.py
tmt/exceptions/__init__.py
tmt/history/__init__.py
tmt/history/context.py
tmt/history/snapshot.py
tmt/history/utils.py
tmt/info/__init__.py
tmt/interface/__init__.py
tmt/interface/tui/__init__.py
tmt/interface/tui/base.py
tmt/interface/tui/entry_display.py
tmt/interface/tui/main.py
tmt/interface/tui/search.py
tmt/storage/__init__.py
tmt/storage/json_db.py
tmt/storage/schema.py
tmt/utils/__init__.py
tmt/utils/duplicates.py
tmt/utils/manager.py
ThatMetricTimeline-0.1.8.dist-info/LICENSE
ThatMetricTimeline-0.1.8.dist-info/METADATA
ThatMetricTimeline-0.1.8.dist-info/WHEEL
ThatMetricTimeline-0.1.8.dist-info/entry_points.txt
ThatMetricTimeline-0.1.8.dist-info/top_level.txt
ThatMetricTimeline-0.1.8.dist-info/RECORD
