Metadata-Version: 2.1
Name: ThatMetricTimeline
Version: 0.1.8
Summary: This package is aimed at machine/deep learning practitioners. It helps keeping track of experiments, offering a consistent and automatized way to store and keep track of experiment results, code snapshot backups and more. It also exposes a terminal user interface to search and see previously ran experiments.
Author-email: Alessio Molinari <alessiomolinar@gmail.com>
Project-URL: Homepage, https://github.com/levnikmyskin/that_metric_timeline
Project-URL: Bug Tracker, https://github.com/levnikmyskin/that_metric_timeline/issues
Classifier: Programming Language :: Python :: 3
Classifier: License :: OSI Approved :: GNU General Public License v3 (GPLv3)
Classifier: Operating System :: OS Independent
Requires-Python: >=3.8
License-File: LICENSE
Requires-Dist: prompt-toolkit
Requires-Dist: filelock
Requires-Dist: pyperclip
Requires-Dist: pathspec
